clustering/__init__.py
clustering/dbscan.py
clustering/kmeans.py
clustering/utils.py
IN.clustering-0.0.2.dist-info/METADATA
IN.clustering-0.0.2.dist-info/WHEEL
IN.clustering-0.0.2.dist-info/top_level.txt
IN.clustering-0.0.2.dist-info/RECORD
