Metadata-Version: 2.1
Name: IN.clustering
Version: 0.0.2
Summary: Implementation of K-means, K-means++, DBSCAN clustering algorithms
Author: Illia Nasiri
Requires-Dist: numpy
